AUTHORS.rst
CONTRIBUTING.rst
HISTORY.rst
LICENSE
MANIFEST.in
README.rst
setup.cfg
setup.py
dataprovider/__init__.py
dataprovider/blend.py
dataprovider/box.py
dataprovider/cli.py
dataprovider/config_data.py
dataprovider/data_augmentation.py
dataprovider/data_provider.py
dataprovider/dataprovider.py
dataprovider/dataset.py
dataprovider/emio.py
dataprovider/forward.py
dataprovider/label_transform.py
dataprovider/misalign.py
dataprovider/parser.py
dataprovider/setup.py
dataprovider/tensor.py
dataprovider/test.py
dataprovider/transform.py
dataprovider/utils.py
dataprovider/vector.py
dataprovider/warp.py
dataprovider.egg-info/PKG-INFO
dataprovider.egg-info/SOURCES.txt
dataprovider.egg-info/dependency_links.txt
dataprovider.egg-info/entry_points.txt
dataprovider.egg-info/not-zip-safe
dataprovider.egg-info/requires.txt
dataprovider.egg-info/top_level.txt
dataprovider/warping/__init__.py
dataprovider/warping/_warping.c
dataprovider/warping/_warping.pyx
dataprovider/warping/warping.c
dataprovider/warping/warping.py
docs/Makefile
docs/authors.rst
docs/conf.py
docs/contributing.rst
docs/dataprovider.rst
docs/dataprovider.warping.rst
docs/history.rst
docs/index.rst
docs/installation.rst
docs/make.bat
docs/modules.rst
docs/readme.rst
docs/usage.rst
docs/_build/html/_static/ajax-loader.gif
docs/_build/html/_static/comment-bright.png
docs/_build/html/_static/comment-close.png
docs/_build/html/_static/comment.png
docs/_build/html/_static/down-pressed.png
docs/_build/html/_static/down.png
docs/_build/html/_static/file.png
docs/_build/html/_static/minus.png
docs/_build/html/_static/plus.png
docs/_build/html/_static/up-pressed.png
docs/_build/html/_static/up.png
tests/__init__.py
tests/test_dataprovider.py