Metadata-Version: 1.1
Name: dataprovider
Version: 0.1.5
Summary: Deep learning platform-independent volumetric data provider for training 3D convolutional network.
Home-page: https://github.com/tartavull/dataprovider
Author: Seung Lab
Author-email: tartavull@gmail.com
License: MIT license
Keywords: dataprovider
Platform: UNKNOWN
Classifier: Development Status :: 2 - Pre-Alpha
Classifier: Intended Audience :: Developers
Classifier: License :: OSI Approved :: MIT License
Classifier: Natural Language :: English
Classifier: Programming Language :: Python :: 2
Classifier: Programming Language :: Python :: 2.6
Classifier: Programming Language :: Python :: 2.7
Classifier: Programming Language :: Python :: 3
Classifier: Programming Language :: Python :: 3.3
Classifier: Programming Language :: Python :: 3.4
Classifier: Programming Language :: Python :: 3.5
